{
    "os": "macOS-11.6-x86_64-i386-64bit",
    "python": "3.9.7",
    "heartbeatAt": "2021-12-02T02:34:03.754733",
    "startedAt": "2021-12-02T02:34:01.917008",
    "docker": null,
    "cpu_count": 4,
    "cuda": null,
    "args": [
        "-s",
        "-vv",
        "."
    ],
    "state": "running",
    "program": "<python with no main file>",
    "git": {
        "remote": "https://github.com/tugrulguner/udacity_repo.git",
        "commit": "a4ad8abf6e6996e1193c534b7a5f0c135031eeb9"
    },
    "email": "tugrulgunr@gmail.com",
    "root": "/Users/ozgecaylioglu/Desktop/GitHub_Projects/udacity_repo",
    "host": "Ozgnr.local",
    "username": "ozgecaylioglu",
    "executable": "/opt/anaconda3/envs/mlflow-7398531e5288219e428182dc4d6601ae57991d39/bin/python"
}
